hoyo_daily_logins_helper/__init__.py
hoyo_daily_logins_helper/__main__.py
hoyo_daily_logins_helper/_version.py
hoyo_daily_logins_helper/consts.py
hoyo_daily_logins_helper/games.py
hoyo_daily_logins_helper/http.py
hoyo_daily_logins_helper/main.py
hoyo_daily_logins_helper/notifications.py
hoyo_daily_logins_helper/scheduler.py
hoyo_daily_logins_helper/utils.py
hoyo_daily_logins_helper-2.9.2.dist-info/LICENSE
hoyo_daily_logins_helper-2.9.2.dist-info/METADATA
hoyo_daily_logins_helper-2.9.2.dist-info/WHEEL
hoyo_daily_logins_helper-2.9.2.dist-info/entry_points.txt
hoyo_daily_logins_helper-2.9.2.dist-info/RECORD
