Metadata-Version: 2.1
Name: hoyo-daily-logins-helper
Version: 2.9.2
Summary: Get hoyo daily login rewards automatically!
Home-page: https://gitlab.com/atomicptr/hoyo-daily-logins-helper
License: GPL-3.0-or-later
Keywords: genshin,genshin-impact,starrail,honkai-starrail,game
Author: Christopher Kaster
Author-email: me@atomicptr.de
Requires-Python: >=3.12,<4.0
Classifier: License :: OSI Approved :: GNU General Public License v3 (GPLv3)
Classifier: License :: OSI Approved :: GNU General Public License v3 or later (GPLv3+)
Classifier: Programming Language :: Python :: 3
Classifier: Programming Language :: Python :: 3.12
Requires-Dist: comboparse (>=1.0,<2.0)
Requires-Dist: pytz (>=2024,<2025)
Requires-Dist: requests (>=2.32,<3.0)
Requires-Dist: scheduler (>=0.8,<0.9)
Project-URL: Repository, https://gitlab.com/atomicptr/hoyo-daily-logins-helper
